odoo/addons/l10n_it_withholding_tax_reason/README.rst
odoo/addons/l10n_it_withholding_tax_reason/__init__.py
odoo/addons/l10n_it_withholding_tax_reason/__manifest__.py
odoo/addons/l10n_it_withholding_tax_reason/i18n/de.po
odoo/addons/l10n_it_withholding_tax_reason/i18n/it.po
odoo/addons/l10n_it_withholding_tax_reason/i18n/l10n_it_withholding_tax_reason.pot
odoo/addons/l10n_it_withholding_tax_reason/models/__init__.py
odoo/addons/l10n_it_withholding_tax_reason/models/withholding_tax.py
odoo/addons/l10n_it_withholding_tax_reason/readme/CONTRIBUTORS.md
odoo/addons/l10n_it_withholding_tax_reason/readme/DESCRIPTION.md
odoo/addons/l10n_it_withholding_tax_reason/readme/INSTALL.md
odoo/addons/l10n_it_withholding_tax_reason/static/description/icon.png
odoo/addons/l10n_it_withholding_tax_reason/static/description/index.html
odoo/addons/l10n_it_withholding_tax_reason/views/withholding_tax.xml
odoo_addon_l10n_it_withholding_tax_reason-16.0.1.0.0.9.dist-info/METADATA
odoo_addon_l10n_it_withholding_tax_reason-16.0.1.0.0.9.dist-info/WHEEL
odoo_addon_l10n_it_withholding_tax_reason-16.0.1.0.0.9.dist-info/top_level.txt
odoo_addon_l10n_it_withholding_tax_reason-16.0.1.0.0.9.dist-info/RECORD
